{
  "project_info": {
    "project_number": "91258372563",
    "project_id": "taminum-app",
    "storage_bucket": "taminum-app.firebasestorage.app"
  },
  "client": [
    {
      "client_info": {
        "mobilesdk_app_id": "1:91258372563:android:fb46d0ade65cdd98d2ef26",
        "android_client_info": {
          "package_name": "com.example.flutter_taminum_mobile"
        }
      },
      "oauth_client": [],
      "api_key": [
        {
          "current_key": "AIzaSyB8PrEg934wwomyod5yJSzQN47QKtCybhk"
        }
      ],
      "services": {
        "appinvite_service": {
          "other_platform_oauth_client": []
        }
      }
    }
  ],
  "configuration_version": "1"
}